LICENSE
README.md
enet.pyx
pyproject.toml
setup.py
enet/callbacks.c
enet/compress.c
enet/host.c
enet/list.c
enet/packet.c
enet/peer.c
enet/protocol.c
enet/unix.c
enet/win32.c
enetython.egg-info/PKG-INFO
enetython.egg-info/SOURCES.txt
enetython.egg-info/dependency_links.txt
enetython.egg-info/requires.txt
enetython.egg-info/top_level.txt